jhproxy/__init__.py
jhproxy/proxy.py
jhproxy/spawners.py
jhproxy-0.1.1.dist-info/METADATA
jhproxy-0.1.1.dist-info/RECORD
jhproxy-0.1.1.dist-info/WHEEL
jhproxy-0.1.1.dist-info/top_level.txt
