Metadata-Version: 2.1
Name: jhproxy
Version: 0.1.1
Summary: A port proxy for JupyterHub when using the DockerSpawner, optionally with (token-based) authorization.
Home-page: https://github.com/aiidalab/jhproxy
Author: Giovanni Pizzi
License: MIT
Keywords: jupyterhub,proxy,authorization,token
Platform: UNKNOWN
Classifier: Programming Language :: Python :: 3
Classifier: Programming Language :: Python :: 3.5
Classifier: License :: OSI Approved :: MIT License
Requires-Dist: jupyterhub
Requires-Dist: dockerspawner
Requires-Dist: traitlets
